LICENSE
MANIFEST.in
README.rst
setup.py
wiz_cli/__init__.py
wiz_cli/functions.py
wiz_cli/init_utils.py
wiz_cli/logger.py
wiz_cli/login_utils.py
wiz_cli/main.py
wiz_cli/parse_utils.py
wiz_cli/print_utils.py
wiz_cli/setting_utils.py
wiz_cli/upload_utils.py
wiznote_cli.egg-info/PKG-INFO
wiznote_cli.egg-info/SOURCES.txt
wiznote_cli.egg-info/dependency_links.txt
wiznote_cli.egg-info/entry_points.txt
wiznote_cli.egg-info/requires.txt
wiznote_cli.egg-info/top_level.txt